dicom_upload/__init__.py
dicom_upload/_frontend.py
dicom_upload/_version.py
dicom_upload/widget_upload.py
dicom_upload/static/extension.js
dicom_upload/static/index.js
dicom_upload/static/index.js.map
dicom_upload-0.2.0.data/data/etc/jupyter/nbconfig/notebook.d/dicom-upload.json
dicom_upload-0.2.0.data/data/share/jupyter/nbextensions/dicom-upload/extension.js
dicom_upload-0.2.0.data/data/share/jupyter/nbextensions/dicom-upload/index.js
dicom_upload-0.2.0.data/data/share/jupyter/nbextensions/dicom-upload/index.js.map
dicom_upload-0.2.0.dist-info/LICENSE.txt
dicom_upload-0.2.0.dist-info/METADATA
dicom_upload-0.2.0.dist-info/WHEEL
dicom_upload-0.2.0.dist-info/top_level.txt
dicom_upload-0.2.0.dist-info/RECORD
