Metadata-Version: 2.1
Name: dicom-upload
Version: 0.2.0
Summary: Upload DICOM files with patient und study data removed from header
Home-page: https://gitlab.version.fz-juelich.de/jupyter4jsc/j4j_extras/dicom-upload
Author: Juelich Supercomputing Centre (JSC)
Author-email: a.grosch@fz-juelich.de
License: UNKNOWN
Keywords: ipython,jupyter,widgets
Platform: UNKNOWN
Classifier: Development Status :: 4 - Beta
Classifier: Framework :: IPython
Classifier: Intended Audience :: Developers
Classifier: Intended Audience :: Science/Research
Classifier: Topic :: Multimedia :: Graphics
Classifier: Programming Language :: Python :: 2
Classifier: Programming Language :: Python :: 2.7
Classifier: Programming Language :: Python :: 3
Classifier: Programming Language :: Python :: 3.3
Classifier: Programming Language :: Python :: 3.4
Classifier: Programming Language :: Python :: 3.5
Classifier: Programming Language :: Python :: 3.6
Classifier: Programming Language :: Python :: 3.7
Requires-Dist: ipywidgets (>=7.0.0)
